systemlogger/__init__.py
systemlogger-0.2.2.dist-info/LICENSE
systemlogger-0.2.2.dist-info/METADATA
systemlogger-0.2.2.dist-info/WHEEL
systemlogger-0.2.2.dist-info/RECORD
