Metadata-Version: 2.3
Name: SystemLogger
Version: 0.2.2
Summary: Create and configure a logger using a global configuration file.
License: CECILL-B
Author: Matthieu Gallet
Author-email: github@19pouces.net
Maintainer: Matthieu Gallet
Maintainer-email: github@19pouces.net
Requires-Python: >=3.8,<4.0
Classifier: Development Status :: 5 - Production/Stable
Classifier: License :: CeCILL-B Free Software License Agreement (CECILL-B)
Classifier: License :: OSI Approved :: CEA CNRS Inria Logiciel Libre License, version 2.1 (CeCILL-2.1)
Classifier: Operating System :: MacOS :: MacOS X
Classifier: Operating System :: POSIX :: BSD
Classifier: Operating System :: POSIX :: Linux
Classifier: Operating System :: Unix
Classifier: Programming Language :: Python :: 3
Classifier: Programming Language :: Python :: 3.8
Classifier: Programming Language :: Python :: 3.9
Classifier: Programming Language :: Python :: 3.10
Classifier: Programming Language :: Python :: 3.11
Classifier: Programming Language :: Python :: 3.12
Classifier: Programming Language :: Python :: 3.13
Classifier: Programming Language :: Python :: 3 :: Only
Requires-Dist: python-logging-loki (>=0.3.1,<0.4.0)
Requires-Dist: sentry-sdk (>=2.22.0,<3.0.0)
Project-URL: Documentation, https://github.com/d9pouces/SystemLogger
Project-URL: Repository, https://github.com/d9pouces/SystemLogger
